tsnet/__init__.py
tsnet/network/__init__.py
tsnet/network/control.py
tsnet/network/discretize.py
tsnet/network/model.py
tsnet/network/topology.py
tsnet/postprocessing/__init__.py
tsnet/postprocessing/detect_cusum.py
tsnet/postprocessing/time_history.py
tsnet/simulation/__init__.py
tsnet/simulation/initialize.py
tsnet/simulation/main.py
tsnet/simulation/single.py
tsnet/simulation/solver.py
tsnet/utils/__init__.py
tsnet/utils/calc_parabola_vertex.py
tsnet/utils/memo.py
tsnet/utils/print_time_delta.py
tsnet/utils/valve_curve.py
tsnet-0.3.1.dist-info/AUTHORS.rst
tsnet-0.3.1.dist-info/LICENSE
tsnet-0.3.1.dist-info/METADATA
tsnet-0.3.1.dist-info/WHEEL
tsnet-0.3.1.dist-info/top_level.txt
tsnet-0.3.1.dist-info/RECORD
