Metadata-Version: 2.1
Name: tsnet
Version: 0.3.1
Summary: tsnet conducts transient simulation using MOC method for water distribution systems.
Home-page: https://github.com/glorialulu/TSNet
Author: Lu Xing
Author-email: xinglu@utexas.edu
License: MIT license
Keywords: tsnet
Classifier: Development Status :: 2 - Pre-Alpha
Classifier: Intended Audience :: Developers
Classifier: License :: OSI Approved :: MIT License
Classifier: Natural Language :: English
Classifier: Programming Language :: Python :: 3
Classifier: Programming Language :: Python :: 3.10
Classifier: Programming Language :: Python :: 3.11
License-File: LICENSE
License-File: AUTHORS.rst
Requires-Dist: pandas
Requires-Dist: numpy
Requires-Dist: scipy
Requires-Dist: matplotlib
Requires-Dist: plotly
Requires-Dist: wntr
Requires-Dist: networkx
